cone.tile-1.2-py3.9-nspkg.pth
cone/tile/__init__.py
cone/tile/_api.py
cone/tile/testdata/tile1.pt
cone/tile/testdata/tile1_override.pt
cone/tile/testdata/tile2.pt
cone/tile/testdata/tile3.pt
cone/tile/testdata/tile4.pt
cone/tile/testdata/tile_exc_bug.pt
cone/tile/testdata/tmpl1.pt
cone/tile/testdata/tmpl2.pt
cone/tile/tests/__init__.py
cone/tile/tests/test_package.py
cone_tile-1.2.dist-info/licenses/LICENSE.rst
cone_tile-1.2.dist-info/METADATA
cone_tile-1.2.dist-info/WHEEL
cone_tile-1.2.dist-info/namespace_packages.txt
cone_tile-1.2.dist-info/top_level.txt
cone_tile-1.2.dist-info/RECORD
