Metadata-Version: 2.4
Name: cone.tile
Version: 1.2
Summary: Tiles for use in pyramid framework.
Home-page: http://github.com/conestack/cone.tile
Author: Cone Contributors
Author-email: dev@conestack.org
License: Simplified BSD
Classifier: Environment :: Web Environment
Classifier: Operating System :: OS Independent
Classifier: Programming Language :: Python
Classifier: Topic :: Internet :: WWW/HTTP :: Dynamic Content
License-File: LICENSE.rst
Requires-Dist: setuptools
Requires-Dist: zope.component
Requires-Dist: zope.deprecation
Requires-Dist: zope.exceptions
Requires-Dist: pyramid<1.10,>=1.5
Requires-Dist: pyramid_chameleon
Provides-Extra: test
Requires-Dist: pytest; extra == "test"
Requires-Dist: cone.app[lxml]<1.1.0,>=1.0.3; extra == "test"
Requires-Dist: zope.pytestlayer; extra == "test"
Dynamic: author
Dynamic: author-email
Dynamic: classifier
Dynamic: description
Dynamic: home-page
Dynamic: keywords
Dynamic: license
Dynamic: license-file
Dynamic: provides-extra
Dynamic: requires-dist
Dynamic: summary
